[
  {
    "path": "posts/2020-08-10-how-to-make-web-ready-us-county-level-maps/",
    "title": "How to make web-ready US county-level maps",
    "description": "Here, I will describe 3 workflows to get you up and running in making fast, web-ready maps.",
    "author": [
      {
        "name": "Asmae Toumi",
        "url": "https://twitter.com/asmae_toumi"
      }
    ],
    "date": "2020-10-13",
    "categories": [],
    "preview": {},
    "last_modified": "2020-10-13T00:25:15-04:00",
    "input_file": {}
  },
  {
    "path": "posts/welcome/",
    "title": "Welcome",
    "description": "I'm here to share data science stuff",
    "author": [
      {
        "name": "Asmae Toumi",
        "url": "https://twitter.com/asmae_toumi"
      }
    ],
    "date": "2020-08-03",
    "categories": [],
    "preview": {},
    "last_modified": "2020-08-10T18:27:54-04:00",
    "input_file": {}
  }
]
